intake_nwp/__init__.py
intake_nwp/cli.py
intake_nwp/utils.py
intake_nwp/source/__init__.py
intake_nwp/source/base.py
intake_nwp/source/nwp.py
intake_nwp-0.5.1.dist-info/licenses/AUTHORS.rst
intake_nwp-0.5.1.dist-info/licenses/LICENSE
intake_nwp-0.5.1.dist-info/METADATA
intake_nwp-0.5.1.dist-info/WHEEL
intake_nwp-0.5.1.dist-info/entry_points.txt
intake_nwp-0.5.1.dist-info/top_level.txt
intake_nwp-0.5.1.dist-info/RECORD
