Metadata-Version: 2.4
Name: intake-nwp
Version: 0.5.1
Summary: Intake drivers for numerical weather prediction data
Author-email: Oceanum Developers <developers@oceanum.science>
Maintainer-email: Oceanum Developers <developers@oceanum.science>
License: MIT License
Project-URL: bugs, https://github.com/oceanum/intake_nwp/issues
Project-URL: changelog, https://github.com/oceanum/intake_nwp/blob/master/changelog.md
Project-URL: homepage, https://github.com/oceanum/intake_nwp
Keywords: nwp,intake,model,download
Classifier: Development Status :: 3 - Alpha
Classifier: Intended Audience :: Science/Research
Classifier: License :: OSI Approved :: MIT License
Classifier: Natural Language :: English
Classifier: Operating System :: OS Independent
Classifier: Topic :: Scientific/Engineering
Classifier: Topic :: Scientific/Engineering :: Physics
Classifier: Topic :: Scientific/Engineering :: Visualization
Classifier: Programming Language :: Python :: 3
Classifier: Programming Language :: Python :: 3.10
Classifier: Programming Language :: Python :: 3.11
Classifier: Programming Language :: Python :: 3.12
Classifier: Programming Language :: Python :: 3.13
License-File: LICENSE
License-File: AUTHORS.rst
Requires-Dist: click
Requires-Dist: cartopy
Requires-Dist: cfgrib
Requires-Dist: herbie-data
Requires-Dist: intake
Requires-Dist: jinja2
Requires-Dist: psutil
Provides-Extra: dev
Requires-Dist: coverage; extra == "dev"
Requires-Dist: mypy; extra == "dev"
Requires-Dist: pytest; extra == "dev"
Requires-Dist: ruff; extra == "dev"
Requires-Dist: sphinx; extra == "dev"
Requires-Dist: tox; extra == "dev"
Requires-Dist: twine; extra == "dev"
Dynamic: license-file
